asrbench/__init__.py
asrbench/abc_benchmark.py
asrbench/benchmark.py
asrbench/benchmark_ctx.py
asrbench/config_loader.py
asrbench/dataset.py
asrbench/jiwer_.py
asrbench/observer.py
asrbench/output_ctx.py
asrbench/report/__init__.py
asrbench/report/components.py
asrbench/report/input_.py
asrbench/report/plots/__init__.py
asrbench/report/plots/appearance.py
asrbench/report/plots/colors_.py
asrbench/report/plots/strategy.py
asrbench/report/report_data.py
asrbench/report/report_template.py
asrbench/report/template_loader.py
asrbench/report/templates/configs.html
asrbench/report/templates/default.html
asrbench/report/templates/infos.html
asrbench/report/templates/mean_table.html
asrbench/report/templates/plot.html
asrbench/report/templates/styles.css
asrbench/transcribe.py
asrbench/transcribers/__init__.py
asrbench/transcribers/abc_factory.py
asrbench/transcribers/abc_transcriber.py
asrbench/transcribers/factory.py
asrbench/transcribers/registry.py
asrbench/utils.py
asrbench-0.1.0.dist-info/LICENSE
asrbench-0.1.0.dist-info/METADATA
asrbench-0.1.0.dist-info/WHEEL
asrbench-0.1.0.dist-info/RECORD
