Metadata-Version: 2.1
Name: asrbench
Version: 0.1.0
Summary: Extensible, easy to use Python framework for evaluation of audio transcription systems.
License: MIT
Author: ASRBench
Author-email: asrbenchmark@gmail.com
Requires-Python: >=3.12,<4.0
Classifier: Development Status :: 5 - Production/Stable
Classifier: License :: OSI Approved :: MIT License
Classifier: Natural Language :: English
Classifier: Operating System :: OS Independent
Classifier: Programming Language :: Python :: 3
Classifier: Programming Language :: Python :: 3.12
Classifier: Topic :: System :: Benchmark
Requires-Dist: jinja2 (>=3.1.4,<4.0.0)
Requires-Dist: jiwer (>=3.0.4,<4.0.0)
Requires-Dist: num2words (>=0.5.13,<0.6.0)
Requires-Dist: pandas (>=2.2.3,<3.0.0)
Requires-Dist: pydub (>=0.25.1,<0.26.0)
Requires-Dist: seaborn (>=0.13.2,<0.14.0)
Requires-Dist: weasyprint (>=62.3,<63.0)
Project-URL: Bug Tracker, https://github.com/ASRBench/asrbench/issues
Project-URL: Documentation, https://asrbench.github.io/asrbench
Project-URL: Source, https://github.com/ASRBench/asrbench
